Metadata-Version: 1.0
Name: gauss-bin-prob-dist2020
Version: 0.1
Summary: Gaussian and Binomial distributions
Home-page: UNKNOWN
Author: Sonia Agrawal
Author-email: UNKNOWN
License: UNKNOWN
Platform: UNKNOWN
